Workbook

Sheet EOQ_Calculator
A1: Economic Order Quantity (EOQ) & Safety Stock Calculator
A2: EOQ = SQRT((2 x Annual Demand x Ordering Cost) / Holding Cost) | Safety Stock = (Max Daily Demand x Max Lead Time) - (Avg Daily Demand x Avg Lead Time)
A4: Legend: | B4: Blue = input cell (editable) | D4: Black = live formula | F4: Yellow = key assumption
A6: SKU_ID | B6: Product Name | C6: Category | D6: Annual Demand (units/yr) | E6: Ordering Cost ($/order) | F6: Holding Cost ($/unit/yr) | G6: EOQ (units/order) | H6: Max Daily Demand | I6: Avg Daily Demand | J6: Max Lead Time (days) | K6: Avg Lead Time (days) | L6: Safety Stock (units)
A7: SKU-1001 | B7: Diamondback Bike | C7: Fitness | D7: 4200 | E7: 75 | F7: 6.2 | G7: =SQRT((2*D7*E7)/F7) -> 318.76779 | H7: 28 | I7: 12 | J7: 9 | K7: 5 | L7: =(H7*J7)-(I7*K7) -> 192
A8: SKU-1002 | B8: Perfect Fitness Trainer | C8: Fitness | D8: 6100 | E8: 60 | F8: 3.1 | G8: =SQRT((2*D8*E8)/F8) -> 485.9311 | H8: 35 | I8: 17 | J8: 8 | K8: 4 | L8: =(H8*J8)-(I8*K8) -> 212
A9: SKU-1003 | B9: Nike Men's Shorts | C9: Apparel | D9: 9800 | E9: 40 | F9: 1.85 | G9: =SQRT((2*D9*E9)/F9) -> 650.98678 | H9: 55 | I9: 27 | J9: 6 | K9: 3 | L9: =(H9*J9)-(I9*K9) -> 249
A10: SKU-1004 | B10: Field & Stream Tent | C10: Outdoor | D10: 2300 | E10: 90 | F10: 8.4 | G10: =SQRT((2*D10*E10)/F10) -> 222.00386 | H10: 18 | I10: 7 | J10: 11 | K10: 6 | L10: =(H10*J10)-(I10*K10) -> 156
A11: SKU-1005 | B11: Under Armour Hoodie | C11: Apparel | D11: 7400 | E11: 45 | F11: 2.4 | G11: =SQRT((2*D11*E11)/F11) -> 526.78269 | H11: 42 | I11: 20 | J11: 7 | K11: 4 | L11: =(H11*J11)-(I11*K11) -> 214
A12: SKU-1006 | B12: Yoga Mat Premium | C12: Fitness | D12: 5600 | E12: 35 | F12: 1.2 | G12: =SQRT((2*D12*E12)/F12) -> 571.54761 | H12: 32 | I12: 15 | J12: 5 | K12: 3 | L12: =(H12*J12)-(I12*K12) -> 115
A13: SKU-1007 | B13: Coleman Cooler 50QT | C13: Outdoor | D13: 3100 | E13: 70 | F13: 5.6 | G13: =SQRT((2*D13*E13)/F13) -> 278.38822 | H13: 22 | I13: 9 | J13: 10 | K13: 5 | L13: =(H13*J13)-(I13*K13) -> 175
A14: SKU-1008 | B14: Wilson Golf Balls (Dz) | C14: Sports Equipment | D14: 8900 | E14: 30 | F14: 0.95 | G14: =SQRT((2*D14*E14)/F14) -> 749.7368 | H14: 48 | I14: 24 | J14: 6 | K14: 3 | L14: =(H14*J14)-(I14*K14) -> 216
A15: SKU-1009 | B15: Nike Dri-FIT Polo | C15: Apparel | D15: 6700 | E15: 38 | F15: 2.1 | G15: =SQRT((2*D15*E15)/F15) -> 492.41871 | H15: 38 | I15: 18 | J15: 7 | K15: 4 | L15: =(H15*J15)-(I15*K15) -> 194
A16: SKU-1010 | B16: Garmin Running Watch | C16: Electronics | D16: 2900 | E16: 110 | F16: 14.75 | G16: =SQRT((2*D16*E16)/F16) -> 207.97653 | H16: 16 | I16: 8 | J16: 12 | K16: 6 | L16: =(H16*J16)-(I16*K16) -> 144
A19: Portfolio Summary
A20: Average EOQ (units): | D20: =AVERAGE(G7:G16) -> 450.45401
A21: Total Safety Stock (units): | D21: =SUM(L7:L16) -> 1867
A22: Highest Holding Cost SKU: | D22: =INDEX(A7:A16,MATCH(MAX(F7:F16),F7:F16,0)) -> SKU-1010
A24: Assumptions: Annual demand, ordering cost, and holding cost figures are illustrative sample inputs styled on the DataCo Smart Supply Chain schema (order item fields, product category, shipping fields). Replace blue input cells with sourced ERP/WMS extract values.

Sheet Reorder_Point_Model
A1: Reorder Point (ROP) Model
A2: ROP = (Avg Daily Demand x Avg Lead Time) + Safety Stock | Values pulled live from the EOQ_Calculator tab via cross-sheet formulas (green font).
A5: SKU_ID | B5: Product Name | C5: Avg Daily Demand | D5: Avg Lead Time (days) | E5: Safety Stock (units) | F5: Reorder Point (ROP, units) | G5: EOQ (units/order) | H5: Days of Supply at ROP Trigger
A6: =EOQ_Calculator!A7 -> SKU-1001 | B6: =EOQ_Calculator!B7 -> Diamondback Bike | C6: =EOQ_Calculator!I7 -> 12 | D6: =EOQ_Calculator!K7 -> 5 | E6: =EOQ_Calculator!L7 -> 192 | F6: =(C6*D6)+E6 -> 252 | G6: =EOQ_Calculator!G7 -> 318.76779 | H6: =IF(C6=0,0,F6/C6) -> 21
A7: =EOQ_Calculator!A8 -> SKU-1002 | B7: =EOQ_Calculator!B8 -> Perfect Fitness Trainer | C7: =EOQ_Calculator!I8 -> 17 | D7: =EOQ_Calculator!K8 -> 4 | E7: =EOQ_Calculator!L8 -> 212 | F7: =(C7*D7)+E7 -> 280 | G7: =EOQ_Calculator!G8 -> 485.9311 | H7: =IF(C7=0,0,F7/C7) -> 16.470588
A8: =EOQ_Calculator!A9 -> SKU-1003 | B8: =EOQ_Calculator!B9 -> Nike Men's Shorts | C8: =EOQ_Calculator!I9 -> 27 | D8: =EOQ_Calculator!K9 -> 3 | E8: =EOQ_Calculator!L9 -> 249 | F8: =(C8*D8)+E8 -> 330 | G8: =EOQ_Calculator!G9 -> 650.98678 | H8: =IF(C8=0,0,F8/C8) -> 12.222222
A9: =EOQ_Calculator!A10 -> SKU-1004 | B9: =EOQ_Calculator!B10 -> Field & Stream Tent | C9: =EOQ_Calculator!I10 -> 7 | D9: =EOQ_Calculator!K10 -> 6 | E9: =EOQ_Calculator!L10 -> 156 | F9: =(C9*D9)+E9 -> 198 | G9: =EOQ_Calculator!G10 -> 222.00386 | H9: =IF(C9=0,0,F9/C9) -> 28.285714
A10: =EOQ_Calculator!A11 -> SKU-1005 | B10: =EOQ_Calculator!B11 -> Under Armour Hoodie | C10: =EOQ_Calculator!I11 -> 20 | D10: =EOQ_Calculator!K11 -> 4 | E10: =EOQ_Calculator!L11 -> 214 | F10: =(C10*D10)+E10 -> 294 | G10: =EOQ_Calculator!G11 -> 526.78269 | H10: =IF(C10=0,0,F10/C10) -> 14.7
A11: =EOQ_Calculator!A12 -> SKU-1006 | B11: =EOQ_Calculator!B12 -> Yoga Mat Premium | C11: =EOQ_Calculator!I12 -> 15 | D11: =EOQ_Calculator!K12 -> 3 | E11: =EOQ_Calculator!L12 -> 115 | F11: =(C11*D11)+E11 -> 160 | G11: =EOQ_Calculator!G12 -> 571.54761 | H11: =IF(C11=0,0,F11/C11) -> 10.666667
A12: =EOQ_Calculator!A13 -> SKU-1007 | B12: =EOQ_Calculator!B13 -> Coleman Cooler 50QT | C12: =EOQ_Calculator!I13 -> 9 | D12: =EOQ_Calculator!K13 -> 5 | E12: =EOQ_Calculator!L13 -> 175 | F12: =(C12*D12)+E12 -> 220 | G12: =EOQ_Calculator!G13 -> 278.38822 | H12: =IF(C12=0,0,F12/C12) -> 24.444444
A13: =EOQ_Calculator!A14 -> SKU-1008 | B13: =EOQ_Calculator!B14 -> Wilson Golf Balls (Dz) | C13: =EOQ_Calculator!I14 -> 24 | D13: =EOQ_Calculator!K14 -> 3 | E13: =EOQ_Calculator!L14 -> 216 | F13: =(C13*D13)+E13 -> 288 | G13: =EOQ_Calculator!G14 -> 749.7368 | H13: =IF(C13=0,0,F13/C13) -> 12
A14: =EOQ_Calculator!A15 -> SKU-1009 | B14: =EOQ_Calculator!B15 -> Nike Dri-FIT Polo | C14: =EOQ_Calculator!I15 -> 18 | D14: =EOQ_Calculator!K15 -> 4 | E14: =EOQ_Calculator!L15 -> 194 | F14: =(C14*D14)+E14 -> 266 | G14: =EOQ_Calculator!G15 -> 492.41871 | H14: =IF(C14=0,0,F14/C14) -> 14.777778
A15: =EOQ_Calculator!A16 -> SKU-1010 | B15: =EOQ_Calculator!B16 -> Garmin Running Watch | C15: =EOQ_Calculator!I16 -> 8 | D15: =EOQ_Calculator!K16 -> 6 | E15: =EOQ_Calculator!L16 -> 144 | F15: =(C15*D15)+E15 -> 192 | G15: =EOQ_Calculator!G16 -> 207.97653 | H15: =IF(C15=0,0,F15/C15) -> 24
A17: Rows highlighted red have a Reorder Point above the portfolio average and should be prioritized in supplier PO cycles. This tab intentionally contains no hardcoded numbers — every value traces back to EOQ_Calculator inputs, so editing a demand or lead-time assumption there flows through automatically.

Sheet Holding_vs_Stockout_Cost
A1: Holding Cost vs. Stockout Cost Trade-off Model
A2: Annual Holding Cost = Current Stock x Holding Cost/Unit | Expected Stockout Cost = Stockout Probability x (Lost Margin + Customer Loss Penalty) x Annual Demand Exposure
A5: SKU_ID | B5: Current Stock (units) | C5: Unit Cost ($) | D5: Selling Price ($) | E5: Holding Cost ($/unit/yr) | F5: Annual Holding Cost ($) | G5: Stockout Probability (%) | H5: Avg Daily Demand | I5: Annual Demand Exposure (units) | J5: Gross Margin ($/unit) | K5: Customer Loss Factor (%) | L5: Expected Annual Stockout Cost ($) | M5: Net Cost Delta ($)
A6: SKU-1001 | B6: 60 | C6: 185 | D6: 299.99 | E6: 6.2 | F6: =B6*E6 -> 372 | G6: 0.12 | H6: 12 | I6: =H6*365 -> 4380 | J6: =D6-C6 -> 114.99 | K6: 0.08 | L6: =G6*(J6*(1+K6))*I6 -> 65273.844 | M6: =F6-L6 -> -64901.844
A7: SKU-1002 | B7: 90 | C7: 58 | D7: 89.99 | E7: 3.1 | F7: =B7*E7 -> 279 | G7: 0.18 | H7: 17 | I7: =H7*365 -> 6205 | J7: =D7-C7 -> 31.99 | K7: 0.06 | L7: =G7*(J7*(1+K7))*I7 -> 37873.409 | M7: =F7-L7 -> -37594.409
A8: SKU-1003 | B8: 140 | C8: 22.5 | D8: 34.99 | E8: 1.85 | F8: =B8*E8 -> 259 | G8: 0.25 | H8: 27 | I8: =H8*365 -> 9855 | J8: =D8-C8 -> 12.49 | K8: 0.04 | L8: =G8*(J8*(1+K8))*I8 -> 32003.127 | M8: =F8-L8 -> -31744.127
A9: SKU-1004 | B9: 40 | C9: 210 | D9: 349.99 | E9: 8.4 | F9: =B9*E9 -> 336 | G9: 0.09 | H9: 7 | I9: =H9*365 -> 2555 | J9: =D9-C9 -> 139.99 | K9: 0.1 | L9: =G9*(J9*(1+K9))*I9 -> 35409.771 | M9: =F9-L9 -> -35073.771
A10: SKU-1005 | B10: 110 | C10: 34 | D10: 54.99 | E10: 2.4 | F10: =B10*E10 -> 264 | G10: 0.2 | H10: 20 | I10: =H10*365 -> 7300 | J10: =D10-C10 -> 20.99 | K10: 0.05 | L10: =G10*(J10*(1+K10))*I10 -> 32177.67 | M10: =F10-L10 -> -31913.67
A11: SKU-1006 | B11: 75 | C11: 18 | D11: 29.99 | E11: 1.2 | F11: =B11*E11 -> 90 | G11: 0.15 | H11: 15 | I11: =H11*365 -> 5475 | J11: =D11-C11 -> 11.99 | K11: 0.03 | L11: =G11*(J11*(1+K11))*I11 -> 10142.191 | M11: =F11-L11 -> -10052.191
A12: SKU-1007 | B12: 45 | C12: 120 | D12: 199.99 | E12: 5.6 | F12: =B12*E12 -> 252 | G12: 0.11 | H12: 9 | I12: =H12*365 -> 3285 | J12: =D12-C12 -> 79.99 | K12: 0.07 | L12: =G12*(J12*(1+K12))*I12 -> 30927.694 | M12: =F12-L12 -> -30675.694
A13: SKU-1008 | B13: 130 | C13: 15 | D13: 24.99 | E13: 0.95 | F13: =B13*E13 -> 123.5 | G13: 0.3 | H13: 24 | I13: =H13*365 -> 8760 | J13: =D13-C13 -> 9.99 | K13: 0.02 | L13: =G13*(J13*(1+K13))*I13 -> 26778.794 | M13: =F13-L13 -> -26655.294
A14: SKU-1009 | B14: 95 | C14: 28 | D14: 44.99 | E14: 2.1 | F14: =B14*E14 -> 199.5 | G14: 0.17 | H14: 18 | I14: =H14*365 -> 6570 | J14: =D14-C14 -> 16.99 | K14: 0.05 | L14: =G14*(J14*(1+K14))*I14 -> 19924.938 | M14: =F14-L14 -> -19725.438
A15: SKU-1010 | B15: 35 | C15: 249 | D15: 399.99 | E15: 14.75 | F15: =B15*E15 -> 516.25 | G15: 0.08 | H15: 8 | I15: =H15*365 -> 2920 | J15: =D15-C15 -> 150.99 | K15: 0.12 | L15: =G15*(J15*(1+K15))*I15 -> 39503.816 | M15: =F15-L15 -> -38987.566
A18: Portfolio Cost Summary
A19: Total Annual Holding Cost: | D19: =SUM(F6:F15) -> 2691.25
A20: Total Expected Stockout Cost: | D20: =SUM(L6:L15) -> 330015.25
A21: Net Portfolio Position: | D21: =D19-D20 -> -327324
A22: SKUs at Stockout Risk (cost > holding): | D22: =COUNTIF(M6:M15,"<0") -> 10
A24: Green rows: holding investment currently outweighs stockout risk exposure (healthy buffer). Red rows: expected stockout cost exceeds the holding cost being carried — these SKUs are under-protected and are prime candidates for safety stock increases or expedited replenishment. Stockout probability and customer loss factor (highlighted yellow) are modeling assumptions; replace with historical fulfillment data where available.
